{
  "2004": {
    "total": 13251719,
    "rate": 80.28,
    "valid": 12914422,
    "invalid": 337297,
    "民進黨": {
      "total": 6471970,
      "rate": 50.11
    },
    "國民黨": {
      "total": 6442452,
      "rate": 49.89
    }
  },
  "2008": {
    "total": 13221609,
    "rate": 76.33,
    "valid": 13103963,
    "invalid": 117646,
    "民進黨": {
      "total": 5444949,
      "rate": 41.55
    },
    "國民黨": {
      "total": 7659014,
      "rate": 58.44
    }
  },
  "2012": {
    "total": 13452016,
    "rate": 74.38,
    "valid": 13354305,
    "invalid": 97711,
    "民進黨": {
      "total": 6093578,
      "rate": 45.63
    },
    "國民黨": {
      "total": 6891139,
      "rate": 51.6
    },
    "無黨籍": {
      "total": 369588,
      "rate": 2.76
    }
  },
  "2016": {
    "total": 12448302,
    "rate": 66.27,
    "valid": 12284970,
    "invalid": 163332,
    "國民黨": {
      "total": 3813365,
      "rate": 31.04
    },
    "民進黨": {
      "total": 6894744,
      "rate": 56.12
    },
    "親民黨": {
      "total": 1576861,
      "rate": 12.83
    }
  },
  "2020": {
    "total": 14464571,
    "rate": 74.9,
    "valid": 14300940,
    "invalid": 163631,
    "親民黨": {
      "total": 608590,
      "rate": 4.26
    },
    "國民黨": {
      "total": 5522119,
      "rate": 38.61
    },
    "民進黨": {
      "total": 8170231,
      "rate": 57.13
    }
  },
  "2024": {
    "total": 14048311,
    "rate": 71.86,
    "valid": 13947506,
    "invalid": 100805,
    "民眾黨": {
      "total": 3690466,
      "rate": 26.46
    },
    "民進黨": {
      "total": 5586019,
      "rate": 40.05
    },
    "國民黨": {
      "total": 4671021,
      "rate": 33.49
    }
  }
}
